CHANGELOG.md
LICENSE
README.md
asyncmy/__init__.py
asyncmy/auth.py
asyncmy/charset.pxd
asyncmy/charset.pyx
asyncmy/connection.pyx
asyncmy/constants/CLIENT.py
asyncmy/constants/COLUMN.py
asyncmy/constants/COMMAND.py
asyncmy/constants/CR.py
asyncmy/constants/ER.py
asyncmy/constants/FIELD_TYPE.py
asyncmy/constants/FLAG.py
asyncmy/constants/SERVER_STATUS.py
asyncmy/constants/__init__.py
asyncmy/contexts.py
asyncmy/converters.pyx
asyncmy/cursors.pyx
asyncmy/errors.pyx
asyncmy/optionfile.py
asyncmy/pool.pyx
asyncmy/protocol.pyx
asyncmy/replication/__init__.py
asyncmy/replication/binlogstream.py
asyncmy/replication/bitmap.py
asyncmy/replication/column.py
asyncmy/replication/constants.py
asyncmy/replication/errors.py
asyncmy/replication/events.py
asyncmy/replication/gtid.py
asyncmy/replication/packets.py
asyncmy/replication/row_events.py
asyncmy/replication/table.py
asyncmy/replication/utils.py
asyncmy/structs.py
asyncmy/version.py
asyncmy/connection.cpython-310-darwin.so
asyncmy/cursors.c
asyncmy/errors.cpython-310-darwin.so
asyncmy/pool.cpython-310-darwin.so
asyncmy/cursors.cpython-310-darwin.so
asyncmy/protocol.cpython-310-darwin.so
asyncmy/connection.c
asyncmy/protocol.c
asyncmy/converters.c
asyncmy/pool.c
asyncmy/converters.cpython-310-darwin.so
asyncmy/charset.c
asyncmy/errors.c
asyncmy/charset.cpython-310-darwin.so
temp_asyncmy_dev_branch-0.2.6.dist-info/LICENSE
temp_asyncmy_dev_branch-0.2.6.dist-info/WHEEL
temp_asyncmy_dev_branch-0.2.6.dist-info/METADATA
temp_asyncmy_dev_branch-0.2.6.dist-info/RECORD
